spikemetrics/__init__.py
spikemetrics/metrics.py
spikemetrics/utils.py
spikemetrics/version.py
spikemetrics-0.1.2.dist-info/LICENSE
spikemetrics-0.1.2.dist-info/METADATA
spikemetrics-0.1.2.dist-info/WHEEL
spikemetrics-0.1.2.dist-info/top_level.txt
spikemetrics-0.1.2.dist-info/RECORD
