Metadata-Version: 2.1
Name: spikemetrics
Version: 0.1.2
Summary: Python toolkit for computing spike sorting metrics
Home-page: https://github.com/SpikeInterface/spikemetrics
Author: Cole Hurwitz, Alessio Paolo Buccino, Josh Siegle, Matthias Hennig, Jeremy Magland, Samuel Garcia
Author-email: cole.hurwitz@gmail.com
License: UNKNOWN
Platform: UNKNOWN
Classifier: Programming Language :: Python :: 3
Classifier: License :: OSI Approved :: Apache Software License
Classifier: Operating System :: OS Independent
Requires-Dist: numpy
Requires-Dist: scipy
Requires-Dist: pandas
Requires-Dist: scikit-learn
